logfaker/__init__.py
logfaker/core/__init__.py
logfaker/core/config.py
logfaker/core/exceptions.py
logfaker/core/models.py
logfaker/generators/__init__.py
logfaker/generators/content.py
logfaker/generators/queries.py
logfaker/generators/users.py
logfaker/search/__init__.py
logfaker/search/base.py
logfaker/search/elasticsearch.py
logfaker/utils/__init__.py
logfaker/utils/csv.py
logfaker/utils/importer.py
logfaker-0.1.1.dist-info/LICENSE
logfaker-0.1.1.dist-info/METADATA
logfaker-0.1.1.dist-info/WHEEL
logfaker-0.1.1.dist-info/RECORD
