Metadata-Version: 2.3
Name: logfaker
Version: 0.1.1
Summary: Generate realistic test data for search engines, focusing on library catalog search systems
License: MIT
Keywords: search,test-data,elasticsearch,openai,data-generation
Author: rilmayer
Requires-Python: >=3.8,<4.0
Classifier: Development Status :: 4 - Beta
Classifier: Intended Audience :: Developers
Classifier: License :: OSI Approved :: MIT License
Classifier: Programming Language :: Python :: 3
Classifier: Programming Language :: Python :: 3.8
Classifier: Programming Language :: Python :: 3.9
Classifier: Programming Language :: Python :: 3.10
Classifier: Programming Language :: Python :: 3.11
Classifier: Programming Language :: Python :: 3.12
Classifier: Programming Language :: Python :: 3.13
Classifier: Topic :: Software Development :: Libraries :: Python Modules
Classifier: Topic :: Software Development :: Testing
Requires-Dist: elasticsearch (>=8.10.0,<9.0.0)
Requires-Dist: openai (>=1.12.0,<2.0.0)
Requires-Dist: pandas (>=2.0.0,<3.0.0)
Requires-Dist: pydantic (>=2.5.0,<3.0.0)
Project-URL: Homepage, https://github.com/rilmayer/logfaker
Project-URL: Repository, https://github.com/rilmayer/logfaker
